django_auth2/__init__.py
django_auth2/authentication.py
django_auth2/conf.py
django_auth2/default_settings.py
django_auth2/forms.py
django_auth2/middleware.py
django_auth2/models.py
django_auth2/utils.py
django_auth2/views.py
django_auth2/providers/__init__.py
django_auth2/providers/facebook.py
django_auth2/providers/google.py
django_contrib_auth2-1.0.0.dist-info/METADATA
django_contrib_auth2-1.0.0.dist-info/WHEEL
django_contrib_auth2-1.0.0.dist-info/top_level.txt
django_contrib_auth2-1.0.0.dist-info/RECORD
